README.md
setup.py
flurgiwoo/__init__.py
flurgiwoo.egg-info/PKG-INFO
flurgiwoo.egg-info/SOURCES.txt
flurgiwoo.egg-info/dependency_links.txt
flurgiwoo.egg-info/top_level.txt